{
    "Ns": {
        "Puff": {
            "dthrow": {
                "id0": 191
            },
            "uthrow": {
                "id0": 14
            },
            "bthrow": {
                "id0": 58
            },
            "fthrow": {
                "id0": 0
            },
            "pummel": {
                "id0": -1
            },
            "edge": {
                "fast": {
                    "id2": -1,
                    "id1": -1,
                    "id0": -1
                },
                "slow": {
                    "id1": -1,
                    "id0": -1
                }
            },
            "floor": {
                "front_hit2": {
                    "id2": -1,
                    "id1": 83,
                    "id0": 83
                },
                "front_hit1": {
                    "id2": -1,
                    "id1": 83,
                    "id0": 83
                },
                "back_hit2": {
                    "id3": 83,
                    "id2": 83,
                    "id1": 83,
                    "id0": 83
                },
                "back_hit1": {
                    "id3": 83,
                    "id2": 83,
                    "id1": 83,
                    "id0": 83
                }
            },
            "dair": {
                "id0": 9
            },
            "uair": {
                "id0": 49
            },
            "bair": {
                "late": {
                    "id1": 88,
                    "id0": 88
                },
                "clean": {
                    "id1": 39,
                    "id0": 39
                }
            },
            "fair": {
                "hit5": {
                    "id1": 82,
                    "id0": 82
                },
                "hits1_4": {
                    "id1": 244,
                    "id0": 194
                }
            },
            "nair": {
                "late": {
                    "id2": 109,
                    "id1": 109,
                    "id0": 109
                },
                "clean": {
                    "id2": 66,
                    "id1": 66,
                    "id0": 66
                }
            },
            "dsmash": {
                "id0": 76
            },
            "dsmash_charge": {
                "late": {
                    "id0": 343
                },
                "mid": {
                    "id0": 76
                },
                "clean": {
                    "id0": 29
                }
            },
            "usmash": {
                "id0": 159
            },
            "usmash_charge": {
                "late": {
                    "id0": 343
                },
                "mid": {
                    "id0": 159
                },
                "clean": {
                    "id0": 25
                }
            },
            "fsmash": {
                "id3": 18,
                "id2": 24,
                "id1": 30,
                "id0": 37
            },
            "dtilt": {
                "id2": 486,
                "id1": 486,
                "id0": 486
            },
            "utilt": {
                "id1": 49,
                "id0": 49
            },
            "ftilt": {
                "ang_down": {
                    "id1": 76,
                    "id0": 76
                },
                "ang_side": {
                    "id1": 69,
                    "id0": 69
                },
                "ang_up": {
                    "id1": 62,
                    "id0": 62
                }
            },
            "dash": {
                "late": {
                    "id0": 57
                },
                "mid": {
                    "id0": -1
                },
                "clean": {
                    "id2": 133,
                    "id1": 106,
                    "id0": -1
                }
            },
            "jab": {
                "hit3": {
                    "id1": 160,
                    "id0": 160
                },
                "hit2": {
                    "id1": 587,
                    "id0": 587
                },
                "hit1": {
                    "id2": 468,
                    "id1": 468,
                    "id0": 468
                }
            },
            "sideSpecial": {
                "pillar_hits2_12": {
                    "id1": 495,
                    "id0": 495
                },
                "pillar_hit1": {
                    "id0": 459
                },
                "shot": {
                    "id0": 404
                }
            },
            "neutralSpecial": {
                "lvl_25": {
                    "id0": 2
                },
                "lvl_24": {
                    "id0": 4
                },
                "lvl_23": {
                    "id0": 6
                },
                "lvl_22": {
                    "id0": 8
                },
                "lvl_21": {
                    "id0": 10
                },
                "lvl_20": {
                    "id0": 13
                },
                "lvl_19": {
                    "id0": 15
                },
                "lvl_18": {
                    "id0": 17
                },
                "lvl_17": {
                    "id0": 20
                },
                "lvl_16": {
                    "id0": 23
                },
                "lvl_15": {
                    "id0": 25
                },
                "lvl_14": {
                    "id0": 28
                },
                "lvl_13": {
                    "id0": 31
                },
                "lvl_12": {
                    "id0": 35
                },
                "lvl_11": {
                    "id0": 38
                },
                "lvl_10": {
                    "id0": 41
                },
                "lvl_9": {
                    "id0": 45
                },
                "lvl_8": {
                    "id0": 49
                },
                "lvl_7": {
                    "id0": 54
                },
                "lvl_6": {
                    "id0": 59
                },
                "lvl_5": {
                    "id0": 64
                },
                "lvl_4": {
                    "id0": 69
                },
                "lvl_3": {
                    "id0": 76
                },
                "lvl_2": {
                    "id0": 83
                },
                "lvl_1": {
                    "id0": 90
                },
                "lvl_0": {
                    "id0": 99
                }
            },
            "upSpecial2": {
                "late": {
                    "id0": 31
                },
                "early": {
                    "id0": 4
                }
            },
            "upSpecial": {
                "tail": {
                    "id0": -1
                },
                "head": {
                    "id0": 86
                }
            }
        }
    }
}