{
    "Pi": {
        "MrG&W": {
            "dthrow": {
                "id0": 281
            },
            "uthrow": {
                "id0": 95
            },
            "bthrow": {
                "id0": 85
            },
            "fthrow": {
                "id0": 178
            },
            "pummel": {
                "id0": -1
            },
            "edge": {
                "fast": {
                    "id1": -1,
                    "id0": -1
                },
                "slow": {
                    "id1": -1,
                    "id0": -1
                }
            },
            "floor": {
                "front_hit2": {
                    "id2": 83,
                    "id1": 83,
                    "id0": 83
                },
                "front_hit1": {
                    "id2": 83,
                    "id1": 83,
                    "id0": 83
                },
                "back_hit2": {
                    "id2": 83,
                    "id1": 83,
                    "id0": 83
                },
                "back_hit1": {
                    "id2": 83,
                    "id1": 83,
                    "id0": 83
                }
            },
            "dair": {
                "landing": {
                    "id1": -1,
                    "id0": -1
                },
                "airhit": {
                    "id1": 55,
                    "id0": 55
                }
            },
            "uair": {
                "part_3": {
                    "id2": 26,
                    "id1": 26,
                    "id0": 26
                },
                "part_2": {
                    "id2": 26,
                    "id1": 26,
                    "id0": 26
                },
                "part_1": {
                    "id2": 26,
                    "id1": 26,
                    "id0": 26
                }
            },
            "bair": {
                "late": {
                    "id2": 77,
                    "id1": 77,
                    "id0": 77
                },
                "clean": {
                    "id2": 77,
                    "id1": 77,
                    "id0": 77
                }
            },
            "fair": {
                "id1": -1,
                "id0": -1
            },
            "nair": {
                "late": {
                    "id2": 97,
                    "id1": 97,
                    "id0": 97
                },
                "clean": {
                    "id2": 57,
                    "id1": 57,
                    "id0": 57
                }
            },
            "dsmash": {
                "id2": 72,
                "id1": 72,
                "id0": 72
            },
            "usmash": {
                "id1": 21,
                "id0": 15
            },
            "fsmash": {
                "hit6": {
                    "id2": 0,
                    "id1": 0,
                    "id0": 0
                },
                "hits1_5": {
                    "id2": 575,
                    "id1": 575,
                    "id0": 575
                }
            },
            "dtilt": {
                "id2": 108,
                "id1": 108,
                "id0": 108
            },
            "utilt": {
                "id2": 82,
                "id1": 82,
                "id0": 88
            },
            "ftilt": {
                "ang_down": {
                    "id2": 110,
                    "id1": 110,
                    "id0": 110
                },
                "ang_side": {
                    "id2": 98,
                    "id1": 98,
                    "id0": 98
                },
                "ang_up": {
                    "id2": 87,
                    "id1": 87,
                    "id0": 87
                }
            },
            "dash": {
                "id1": 102,
                "id0": 102
            },
            "jab": {
                "id1": 592,
                "id0": 592
            },
            "neutralSpecial": {
                "ground": {
                    "id1": 669,
                    "id0": 669
                },
                "air": {
                    "id0": 754
                }
            },
            "downSpecial": {
                "blast": {
                    "id0": 12
                },
                "lightning": {
                    "id0": 101
                }
            },
            "sideSpecial": {
                "id0": 184
            }
        }
    }
}