{
    "Zd": {
        "Samus": {
            "dthrow": {
                "id0": 274
            },
            "uthrow": {
                "id0": 0
            },
            "bthrow": {
                "id0": 43
            },
            "fthrow": {
                "id0": 72
            },
            "pummel": {
                "id0": -1
            },
            "edge": {
                "fast": {
                    "id3": -1,
                    "id2": -1,
                    "id1": -1,
                    "id0": -1
                },
                "slow": {
                    "id2": -1,
                    "id1": -1,
                    "id0": -1
                }
            },
            "floor": {
                "front_hit2": {
                    "id2": 148,
                    "id1": 115,
                    "id0": 115
                },
                "front_hit1": {
                    "id2": 148,
                    "id1": 148,
                    "id0": 148
                },
                "back_hit2": {
                    "id2": 148,
                    "id1": 148,
                    "id0": 148
                },
                "back_hit1": {
                    "id2": 148,
                    "id1": 148,
                    "id0": 148
                }
            },
            "dair": {
                "id1": 213,
                "id0": 138
            },
            "uair": {
                "id0": 69
            },
            "bair": {
                "id2": 32,
                "id1": 155,
                "id0": 155
            },
            "fair": {
                "id2": 32,
                "id1": 155,
                "id0": 155
            },
            "nair": {
                "hit6": {
                    "id3": 100,
                    "id2": 100,
                    "id1": 89,
                    "id0": 89
                },
                "hits1_5": {
                    "id3": -1,
                    "id2": -1,
                    "id1": -1,
                    "id0": -1
                }
            },
            "dsmash": {
                "hit2": {
                    "id1": 113,
                    "id0": 113
                },
                "hit1": {
                    "id1": 97,
                    "id0": 97
                }
            },
            "usmash": {
                "hit12": {
                    "id3": 59,
                    "id2": 59,
                    "id1": 59,
                    "id0": 59
                },
                "hits7_11": {
                    "id3": -1,
                    "id2": -1,
                    "id1": -1,
                    "id0": -1
                },
                "hits1_6": {
                    "id3": -1,
                    "id2": -1,
                    "id1": -1,
                    "id0": -1
                }
            },
            "fsmash": {
                "hit5": {
                    "id3": 37,
                    "id2": 37,
                    "id1": 37,
                    "id0": 37
                },
                "hits1_4": {
                    "id3": -1,
                    "id2": -1,
                    "id1": -1,
                    "id0": -1
                }
            },
            "dtilt": {
                "id3": 153,
                "id2": 153,
                "id1": 172,
                "id0": 172
            },
            "utilt": {
                "id1": 29,
                "id0": 29
            },
            "ftilt": {
                "id2": 60,
                "id1": 54,
                "id0": 49
            },
            "dash": {
                "late": {
                    "id1": 201,
                    "id0": 180
                },
                "clean": {
                    "id1": 103,
                    "id0": 41
                }
            },
            "jab": {
                "hit3": {
                    "id3": 343,
                    "id2": 343,
                    "id1": 343,
                    "id0": 343
                },
                "hits1_2": {
                    "id3": 343,
                    "id2": 343,
                    "id1": 343,
                    "id0": 343
                }
            },
            "sideSpecial": {
                "id0": 165
            },
            "upSpecial": {
                "air_hit2": {
                    "id0": -1
                },
                "air_hit1": {
                    "id0": -1
                },
                "ground_hit2": {
                    "id0": -1
                },
                "ground_hit1": {
                    "id0": -1
                }
            },
            "neutralSpecial": {
                "hit6": {
                    "id1": 107,
                    "id3": 151,
                    "id2": 151,
                    "id0": 107
                },
                "hits1_5": {
                    "id3": 943,
                    "id2": 943,
                    "id1": -1,
                    "id0": -1
                }
            },
            "unknown": {
                "id0": 129
            }
        }
    }
}